{
    "突击.电场增幅0": {
        "action": "Swipe",
        "begin": [
            328,
            258,
            1,
            1
        ],
        "end": [
            323,
            720,
            1,
            1
        ],
        "next": [
            "突击.电场增幅1"
        ]
    },
    "突击.电场增幅1": {
        "recognition": "OCR",
        "expected": [
            "电场增幅"
        ],
        "roi": [
            183,
            231,
            307,
            304
        ],
        "action": "Click",
        "next": [
            "突击.定向精研选关.下一步1"
        ]
    },
    "突击.制胜追进0": {
        "action": "Swipe",
        "begin": [
            328,
            258,
            1,
            1
        ],
        "end": [
            323,
            720,
            1,
            1
        ],
        "next": [
            "突击.制胜追进1"
        ]
    },
    "突击.制胜追进1": {
        "recognition": "OCR",
        "expected": [
            "制胜追进"
        ],
        "roi": [
            183,
            231,
            307,
            304
        ],
        "action": "Click",
        "next": [
            "突击.定向精研选关.下一步1"
        ]
    },
    "突击.双重对策0": {
        "action": "Swipe",
        "begin": [
            328,
            258,
            1,
            1
        ],
        "end": [
            323,
            720,
            1,
            1
        ],
        "next": [
            "突击.双重对策1"
        ]
    },
    "突击.双重对策1": {
        "recognition": "OCR",
        "expected": [
            "双重对策"
        ],
        "roi": [
            183,
            231,
            307,
            304
        ],
        "action": "Click",
        "next": [
            "突击.定向精研选关.下一步1"
        ]
    },
    "突击.异位打击0": {
        "action": "Swipe",
        "begin": [
            328,
            258,
            1,
            1
        ],
        "end": [
            323,
            720,
            1,
            1
        ],
        "next": [
            "突击.异位打击1"
        ]
    },
    "突击.异位打击1": {
        "recognition": "OCR",
        "expected": [
            "异位打击"
        ],
        "roi": [
            183,
            231,
            307,
            304
        ],
        "action": "Click",
        "next": [
            "突击.定向精研选关.下一步1"
        ]
    },
    "突击.异位提振0": {
        "action": "Swipe",
        "begin": [
            328,
            258,
            1,
            1
        ],
        "end": [
            323,
            720,
            1,
            1
        ],
        "next": [
            "突击.异位提振1"
        ]
    },
    "突击.异位提振1": {
        "action": "Swipe",
        "begin": [
            389,
            508,
            1,
            1
        ],
        "end": [
            391,
            415,
            1,
            1
        ],
        "next": [
            "突击.异位提振2"
        ]
    },
    "突击.异位提振2": {
        "recognition": "OCR",
        "expected": [
            "异位提振"
        ],
        "roi": [
            183,
            231,
            307,
            304
        ],
        "action": "Click",
        "next": [
            "突击.定向精研选关.下一步1"
        ]
    },
    "突击.应急修复0": {
        "action": "Swipe",
        "begin": [
            328,
            258,
            1,
            1
        ],
        "end": [
            323,
            720,
            1,
            1
        ],
        "next": [
            "突击.应急修复1"
        ]
    },
    "突击.应急修复1": {
        "action": "Swipe",
        "begin": [
            389,
            508,
            1,
            1
        ],
        "end": [
            391,
            415,
            1,
            1
        ],
        "next": [
            "突击.应急修复2"
        ]
    },
    "突击.应急修复2": {
        "recognition": "OCR",
        "expected": [
            "应急修复"
        ],
        "roi": [
            183,
            231,
            307,
            304
        ],
        "action": "Click",
        "next": [
            "突击.定向精研选关.下一步1"
        ]
    },
    "突击.减伤支援0": {
        "action": "Swipe",
        "begin": [
            328,
            258,
            1,
            1
        ],
        "end": [
            323,
            720,
            1,
            1
        ],
        "next": [
            "突击.减伤支援1"
        ]
    },
    "突击.减伤支援1": {
        "action": "Swipe",
        "begin": [
            389,
            508,
            1,
            1
        ],
        "end": [
            391,
            415,
            1,
            1
        ],
        "next": [
            "突击.减伤支援2"
        ]
    },
    "突击.减伤支援2": {
        "recognition": "OCR",
        "expected": [
            "减伤支援"
        ],
        "roi": [
            183,
            231,
            307,
            304
        ],
        "action": "Click",
        "next": [
            "突击.定向精研选关.下一步1"
        ]
    },
    "突击.实弹增幅0": {
        "action": "Swipe",
        "begin": [
            328,
            258,
            1,
            1
        ],
        "end": [
            323,
            720,
            1,
            1
        ],
        "next": [
            "突击.实弹增幅1"
        ]
    },
    "突击.实弹增幅1": {
        "action": "Swipe",
        "begin": [
            389,
            508,
            1,
            1
        ],
        "end": [
            391,
            415,
            1,
            1
        ],
        "next": [
            "突击.实弹增幅2"
        ]
    },
    "突击.实弹增幅2": {
        "recognition": "OCR",
        "expected": [
            "实弹增幅"
        ],
        "roi": [
            183,
            231,
            307,
            304
        ],
        "action": "Click",
        "next": [
            "突击.定向精研选关.下一步1"
        ]
    },
    "突击.灼热增幅0": {
        "action": "Swipe",
        "begin": [
            379,
            502,
            1,
            1
        ],
        "end": [
            380,
            0,
            1,
            1
        ],
        "next": [
            "突击.灼热增幅1"
        ]
    },
    "突击.灼热增幅1": {
        "recognition": "OCR",
        "expected": [
            "灼热增幅"
        ],
        "roi": [
            183,
            231,
            307,
            304
        ],
        "action": "Click",
        "next": [
            "突击.定向精研选关.下一步1"
        ]
    },
    "突击.冰点增幅0": {
        "action": "Swipe",
        "begin": [
            379,
            502,
            1,
            1
        ],
        "end": [
            380,
            0,
            1,
            1
        ],
        "next": [
            "突击.冰点增幅1"
        ]
    },
    "突击.冰点增幅1": {
        "recognition": "OCR",
        "expected": [
            "冰点增幅"
        ],
        "roi": [
            183,
            231,
            307,
            304
        ],
        "action": "Click",
        "next": [
            "突击.定向精研选关.下一步1"
        ]
    },
    "突击.强蚀增幅0": {
        "action": "Swipe",
        "begin": [
            379,
            502,
            1,
            1
        ],
        "end": [
            380,
            0,
            1,
            1
        ],
        "next": [
            "突击.强蚀增幅1"
        ]
    },
    "突击.强蚀增幅1": {
        "recognition": "OCR",
        "expected": [
            "强蚀增幅"
        ],
        "roi": [
            183,
            231,
            307,
            304
        ],
        "action": "Click",
        "next": [
            "突击.定向精研选关.下一步1"
        ]
    },
    "突击.激流增幅0": {
        "action": "Swipe",
        "begin": [
            379,
            502,
            1,
            1
        ],
        "end": [
            380,
            0,
            1,
            1
        ],
        "next": [
            "突击.激流增幅1"
        ]
    },
    "突击.激流增幅1": {
        "recognition": "OCR",
        "expected": [
            "激流增幅"
        ],
        "roi": [
            183,
            231,
            307,
            304
        ],
        "action": "Click",
        "next": [
            "突击.定向精研选关.下一步1"
        ]
    }
}